fief/__init__.py
fief/alembic.ini
fief/app.py
fief/errors.py
fief/exceptions.py
fief/forms.py
fief/lifespan.py
fief/locale.py
fief/logger.py
fief/paths.py
fief/py.typed
fief/scheduler.py
fief/settings.py
fief/settings_class.py
fief/templates.py
fief/worker.py
fief/alembic/env.py
fief/alembic/table_prefix_codemod.py
fief/alembic/versions/2023-08-28_initial_migration.py
fief/alembic/versions/2024-01-03_add_adminsessiontoken_and_adminapikey_.py
fief/alembic/versions/2024-08-29_add_unique_constraint_on_oauthaccount_.py
fief/apps/__init__.py
fief/apps/api/__init__.py
fief/apps/api/app.py
fief/apps/api/routers/__init__.py
fief/apps/api/routers/clients.py
fief/apps/api/routers/email_templates.py
fief/apps/api/routers/oauth_providers.py
fief/apps/api/routers/permissions.py
fief/apps/api/routers/roles.py
fief/apps/api/routers/tenants.py
fief/apps/api/routers/user_fields.py
fief/apps/api/routers/users.py
fief/apps/api/routers/webhooks.py
fief/apps/auth/__init__.py
fief/apps/auth/app.py
fief/apps/auth/exception_handlers.py
fief/apps/auth/responses.py
fief/apps/auth/forms/__init__.py
fief/apps/auth/forms/auth.py
fief/apps/auth/forms/password.py
fief/apps/auth/forms/profile.py
fief/apps/auth/forms/register.py
fief/apps/auth/forms/reset.py
fief/apps/auth/forms/verify_email.py
fief/apps/auth/routers/__init__.py
fief/apps/auth/routers/auth.py
fief/apps/auth/routers/dashboard.py
fief/apps/auth/routers/oauth.py
fief/apps/auth/routers/register.py
fief/apps/auth/routers/reset.py
fief/apps/auth/routers/token.py
fief/apps/auth/routers/user.py
fief/apps/auth/routers/well_known.py
fief/apps/dashboard/__init__.py
fief/apps/dashboard/app.py
fief/apps/dashboard/dependencies.py
fief/apps/dashboard/exception_handlers.py
fief/apps/dashboard/responses.py
fief/apps/dashboard/validators.py
fief/apps/dashboard/forms/__init__.py
fief/apps/dashboard/forms/api_key.py
fief/apps/dashboard/forms/client.py
fief/apps/dashboard/forms/email_template.py
fief/apps/dashboard/forms/oauth_provider.py
fief_server-0.30.0.dist-info/METADATA
fief_server-0.30.0.dist-info/WHEEL
fief_server-0.30.0.dist-info/entry_points.txt
fief_server-0.30.0.dist-info/licenses/LICENSE.md
fief_server-0.30.0.dist-info/RECORD
