Metadata-Version: 2.4
Name: fief-server
Version: 0.30.0
Summary: Users and authentication management SaaS
Project-URL: Documentation, https://docs.fief.dev
Project-URL: Source, https://github.com/fief-dev/fief
Author-email: François Voron <contact@fief.dev>
License-File: LICENSE.md
Classifier: Intended Audience :: Developers
Classifier: Programming Language :: Python :: 3 :: Only
Classifier: Programming Language :: Python :: 3.12
Requires-Python: >=3.12
Requires-Dist: aiomysql==0.2.0
Requires-Dist: aiosqlite==0.20.0
Requires-Dist: alembic==1.14.0
Requires-Dist: apscheduler==3.10.4
Requires-Dist: argon2-cffi==23.1.0
Requires-Dist: asgi-babel==0.10.0
Requires-Dist: asyncpg==0.30.0
Requires-Dist: dramatiq[redis]==1.17.1
Requires-Dist: email-validator==2.2.0
Requires-Dist: fastapi==0.115.4
Requires-Dist: fief-client==0.20.0
Requires-Dist: furl==2.1.3
Requires-Dist: httpx-oauth==0.15.1
Requires-Dist: itsdangerous==2.2.0
Requires-Dist: jinja2==3.1.4
Requires-Dist: jwcrypto==1.5.6
Requires-Dist: loguru==0.7.2
Requires-Dist: phonenumbers<8.14,>=8.12.48
Requires-Dist: posthog<4,>=3.0.1
Requires-Dist: postmarker==1.0
Requires-Dist: psycopg2==2.9.10
Requires-Dist: pwdlib[argon2,bcrypt]==0.2.1
Requires-Dist: pycountry<25,>=23
Requires-Dist: pydantic-settings==2.6.1
Requires-Dist: pydantic==2.9.2
Requires-Dist: python-multipart==0.0.17
Requires-Dist: python-slugify==8.0.4
Requires-Dist: pytz==2024.2
Requires-Dist: rich==13.9.4
Requires-Dist: sendgrid==6.11.0
Requires-Dist: sentry-dramatiq==0.3.3
Requires-Dist: sentry-sdk==2.18.0
Requires-Dist: sqlalchemy-utils==0.41.2
Requires-Dist: sqlalchemy[mypy]==2.0.36
Requires-Dist: typer==0.12.5
Requires-Dist: uvicorn[standard]==0.32.0
Requires-Dist: wtforms==3.2.1
Requires-Dist: zxcvbn-rs-py==0.1.1
